gold_tradier/__init__.py
gold_tradier_client-0.0.1.dist-info/METADATA
gold_tradier_client-0.0.1.dist-info/WHEEL
gold_tradier_client-0.0.1.dist-info/top_level.txt
gold_tradier_client-0.0.1.dist-info/RECORD
